jsonschemacodegen/__init__.py
jsonschemacodegen/_version.py
jsonschemacodegen/cpp.py
jsonschemacodegen/json_example.py
jsonschemacodegen/python.py
jsonschemacodegen/resolver.py
jsonschemacodegen/schemawrappers.py
jsonschemacodegen/templates/cpp/__init__.py
jsonschemacodegen/templates/cpp/allof.cpp.jinja2
jsonschemacodegen/templates/cpp/allof.hpp.jinja2
jsonschemacodegen/templates/cpp/anyof.cpp.jinja2
jsonschemacodegen/templates/cpp/anyof.hpp.jinja2
jsonschemacodegen/templates/cpp/array.cpp.jinja2
jsonschemacodegen/templates/cpp/array.hpp.jinja2
jsonschemacodegen/templates/cpp/bool.cpp.jinja2
jsonschemacodegen/templates/cpp/bool.hpp.jinja2
jsonschemacodegen/templates/cpp/constraints.jinja2
jsonschemacodegen/templates/cpp/datetime.cpp.jinja2
jsonschemacodegen/templates/cpp/datetime.hpp.jinja2
jsonschemacodegen/templates/cpp/exceptions.hpp.jinja2
jsonschemacodegen/templates/cpp/header.hpp.jinja2
jsonschemacodegen/templates/cpp/loader.jinja2
jsonschemacodegen/templates/cpp/null.cpp.jinja2
jsonschemacodegen/templates/cpp/null.hpp.jinja2
jsonschemacodegen/templates/cpp/numeric.cpp.jinja2
jsonschemacodegen/templates/cpp/numeric.hpp.jinja2
jsonschemacodegen/templates/cpp/object.cpp.jinja2
jsonschemacodegen/templates/cpp/object.hpp.jinja2
jsonschemacodegen/templates/cpp/oneof.cpp.jinja2
jsonschemacodegen/templates/cpp/oneof.hpp.jinja2
jsonschemacodegen/templates/cpp/propname.jinja2
jsonschemacodegen/templates/cpp/ref.hpp.jinja2
jsonschemacodegen/templates/cpp/source.cpp.jinja2
jsonschemacodegen/templates/cpp/string.cpp.jinja2
jsonschemacodegen/templates/cpp/string.hpp.jinja2
jsonschemacodegen/templates/cpp/string_enum.cpp.jinja2
jsonschemacodegen/templates/cpp/string_enum.hpp.jinja2
jsonschemacodegen/templates/markdown/__init__.py
jsonschemacodegen/templates/markdown/allOf.md.jinja2
jsonschemacodegen/templates/markdown/anyOf.md.jinja2
jsonschemacodegen/templates/markdown/array.md.jinja2
jsonschemacodegen/templates/markdown/boolean.md.jinja2
json_schema_codegen-0.6.3.dist-info/LICENSE
json_schema_codegen-0.6.3.dist-info/METADATA
json_schema_codegen-0.6.3.dist-info/WHEEL
json_schema_codegen-0.6.3.dist-info/top_level.txt
json_schema_codegen-0.6.3.dist-info/RECORD
