Metadata-Version: 2.1
Name: json-schema-codegen
Version: 0.6.3
Summary: Generate C++ or Python structures from JSON-Schema
Home-page: http://github.com/pearmaster/json-schema-codegen
Author: Jacob Brunson
Author-email: pypi@jacobbrunson.com
License: GPLv2
Platform: UNKNOWN
Requires-Python: >=3.7
License-File: LICENSE
Requires-Dist: stringcase
Requires-Dist: jacobs-jinja-too (>=0.0.4)
